LICENSE
json_file_split/__init__.py
json_file_split/main.py
json_file_split/split_libs/jsonl_split.py
json_file_split-0.0.261.dist-info/LICENSE
json_file_split-0.0.261.dist-info/METADATA
json_file_split-0.0.261.dist-info/WHEEL
json_file_split-0.0.261.dist-info/entry_points.txt
json_file_split-0.0.261.dist-info/RECORD
